README.md
setup.cfg
setup.py
ie_mbdbl2018_vandervizioli/__init__.py
ie_mbdbl2018_vandervizioli.egg-info/PKG-INFO
ie_mbdbl2018_vandervizioli.egg-info/SOURCES.txt
ie_mbdbl2018_vandervizioli.egg-info/dependency_links.txt
ie_mbdbl2018_vandervizioli.egg-info/not-zip-safe
ie_mbdbl2018_vandervizioli.egg-info/top_level.txt