Metadata-Version: 1.0
Name: ie-mbdbl2018-vandervizioli
Version: 0.1
Summary: Python Packaging Starting Kit - Simple Structure to create your own package - for training purposes!
Home-page: https://github.com/vandervizioli/ie_mbdbl2018_vandervizioli.git
Author: Vander Vizioli
Author-email: vander.vizioli@student.ie.edu
License: MIT
Platform: UNKNOWN
